REVHubInterface/REV2mSensor.py
REVHubInterface/REVADC.py
REVHubInterface/REVColorSensorV3.py
REVHubInterface/REVComPorts.py
REVHubInterface/REVDIO.py
REVHubInterface/REVI2C.py
REVHubInterface/REVModule.py
REVHubInterface/REVMotor.py
REVHubInterface/REVServo.py
REVHubInterface/REVcomm.py
REVHubInterface/REVmessages.py
REVHubInterface/__init__.py
REVHubInterface/__main__.py
REVHubInterface/__main__.spec
REVHubInterface/_version.py
REVHubInterface/org.unofficialrevport.REVHubInterface.Devel.png
REVHubInterface/org.unofficialrevport.REVHubInterface.png
REVHubInterface-1.4.1.dist-info/LICENSE.txt
REVHubInterface-1.4.1.dist-info/METADATA
REVHubInterface-1.4.1.dist-info/WHEEL
REVHubInterface-1.4.1.dist-info/entry_points.txt
REVHubInterface-1.4.1.dist-info/top_level.txt
REVHubInterface-1.4.1.dist-info/RECORD
