Metadata-Version: 2.1
Name: REVHubInterface
Version: 1.4.1
Summary: GUI program for manual control of REV Robotics Expansion Hub from a PC. Unofficial "Community Edition". 
License: Copyright (c) 2024, Unofficial Rev Port team and contributors.
Project-URL: Homepage, https://unofficialrevport.org
Project-URL: Repository, https://github.com/unofficial-rev-port/REVHubInterface.git
Project-URL: Issues, https://github.com/unofficial-rev-port/REVHubInterface/issues
Keywords: REV,Expansion Hub,Hub Interface
Classifier: Development Status :: 5 - Production/Stable
Classifier: Environment :: X11 Applications
Classifier: Environment :: Win32 (MS Windows)
Classifier: Environment :: MacOS X
Classifier: Intended Audience :: Developers
Classifier: Intended Audience :: Education
Classifier: Intended Audience :: End Users/Desktop
Classifier: Intended Audience :: Science/Research
Classifier: License :: OSI Approved :: BSD License
Classifier: Natural Language :: English
Classifier: Operating System :: OS Independent
Classifier: Programming Language :: Python :: 3
Classifier: Topic :: Education
Classifier: Topic :: Scientific/Engineering
License-File: LICENSE.txt
Requires-Dist: pyserial ==3.5
Requires-Dist: sv-ttk ==2.6.0
